equals/__init__.py
equals/constraints/__init__.py
equals/constraints/anything_false.py
equals/constraints/anything_true.py
equals/constraints/base.py
equals/constraints/containing.py
equals/constraints/containing_only.py
equals/constraints/length.py
equals/constraints/not_containing.py
equals/constraints/numbers/__init__.py
equals/constraints/numbers/between.py
equals/constraints/numbers/greater_than.py
equals/constraints/numbers/greater_than_or_equal.py
equals/constraints/numbers/less_than.py
equals/constraints/numbers/less_than_or_equal.py
equals/constraints/strings/__init__.py
equals/constraints/strings/endswith.py
equals/constraints/strings/regex.py
equals/constraints/strings/startswith.py
equals/constraints/with_attrs.py
equals/equals.py
equals-3.1.1.dist-info/LICENSE
equals-3.1.1.dist-info/METADATA
equals-3.1.1.dist-info/WHEEL
equals-3.1.1.dist-info/RECORD
