Metadata-Version: 2.1
Name: equals
Version: 3.1.1
Summary: Fuzzy Mock objects for testing
Home-page: https://github.com/smartfastlabs/equals
License: MIT
Keywords: testing,mocks,mocking,stubs,stubbing
Author: Todd Sifleet
Author-email: todd@smartfast.com
Maintainer: Todd Sifleet
Maintainer-email: todd@smartfast.com
Requires-Python: >=3.9,<4.0
Classifier: Intended Audience :: Developers
Classifier: License :: OSI Approved :: MIT License
Classifier: Programming Language :: Python
Classifier: Programming Language :: Python :: 3
Classifier: Programming Language :: Python :: 3.9
Classifier: Programming Language :: Python :: 3.10
Classifier: Programming Language :: Python :: 3.11
Classifier: Programming Language :: Python :: 3.12
Classifier: Programming Language :: Python :: 3.13
Classifier: Topic :: Software Development :: Testing
Project-URL: Repository, https://github.com/smartfastlabs/equals
